{"order":20,"type":"object","title":"%configuration.typescript%","properties":{"javascript.implicitProjectConfig.checkJs":{"default":false,"markdownDescription":"%configuration.implicitProjectConfig.checkJs%","scope":"window","markdownDeprecationMessage":"%configuration.javascript.checkJs.checkJs.deprecation%","type":"boolean"},"js\/ts.implicitProjectConfig.checkJs":{"type":"boolean","default":false,"markdownDescription":"%configuration.implicitProjectConfig.checkJs%","scope":"window"},"javascript.implicitProjectConfig.experimentalDecorators":{"default":false,"markdownDescription":"%configuration.implicitProjectConfig.experimentalDecorators%","scope":"window","markdownDeprecationMessage":"%configuration.javascript.checkJs.experimentalDecorators.deprecation%","type":"boolean"},"js\/ts.implicitProjectConfig.experimentalDecorators":{"type":"boolean","default":false,"markdownDescription":"%configuration.implicitProjectConfig.experimentalDecorators%","scope":"window"},"js\/ts.implicitProjectConfig.strictNullChecks":{"type":"boolean","default":true,"markdownDescription":"%configuration.implicitProjectConfig.strictNullChecks%","scope":"window"},"js\/ts.implicitProjectConfig.strictFunctionTypes":{"type":"boolean","default":true,"markdownDescription":"%configuration.implicitProjectConfig.strictFunctionTypes%","scope":"window"},"javascript.suggest.names":{"type":"boolean","default":true,"markdownDescription":"%configuration.suggest.names%","scope":"resource"},"typescript.tsc.autoDetect":{"default":"on","scope":"window","enum":["on","off","build","watch"],"description":"%typescript.tsc.autoDetect%","markdownEnumDescriptions":["%typescript.tsc.autoDetect.on%","%typescript.tsc.autoDetect.off%","%typescript.tsc.autoDetect.build%","%typescript.tsc.autoDetect.watch%"],"type":"string"},"javascript.suggest.paths":{"type":"boolean","default":true,"description":"%configuration.suggest.paths%","scope":"resource"},"javascript.preferences.importModuleSpecifier":{"type":"string","scope":"language-overridable","enum":["shortest","relative","non-relative","project-relative"],"description":"%typescript.preferences.importModuleSpecifier%","markdownEnumDescriptions":["%typescript.preferences.importModuleSpecifier.shortest%","%typescript.preferences.importModuleSpecifier.relative%","%typescript.preferences.importModuleSpecifier.nonRelative%","%typescript.preferences.importModuleSpecifier.projectRelative%"],"default":"shortest"},"typescript.preferences.importModuleSpecifier":{"type":"string","scope":"language-overridable","enum":["shortest","relative","non-relative","project-relative"],"description":"%typescript.preferences.importModuleSpecifier%","markdownEnumDescriptions":["%typescript.preferences.importModuleSpecifier.shortest%","%typescript.preferences.importModuleSpecifier.relative%","%typescript.preferences.importModuleSpecifier.nonRelative%","%typescript.preferences.importModuleSpecifier.projectRelative%"],"default":"shortest"},"javascript.preferences.importModuleSpecifierEnding":{"type":"string","description":"%typescript.preferences.importModuleSpecifierEnding%","scope":"language-overridable","enum":["auto","minimal","index","js"],"default":"auto","enumItemLabels":[null,null,null,"%typescript.preferences.importModuleSpecifierEnding.label.js%"],"markdownEnumDescriptions":["%typescript.preferences.importModuleSpecifierEnding.auto%","%typescript.preferences.importModuleSpecifierEnding.minimal%","%typescript.preferences.importModuleSpecifierEnding.index%","%typescript.preferences.importModuleSpecifierEnding.js%"]},"typescript.preferences.importModuleSpecifierEnding":{"type":"string","description":"%typescript.preferences.importModuleSpecifierEnding%","scope":"language-overridable","enum":["auto","minimal","index","js"],"default":"auto","enumItemLabels":[null,null,null,"%typescript.preferences.importModuleSpecifierEnding.label.js%"],"markdownEnumDescriptions":["%typescript.preferences.importModuleSpecifierEnding.auto%","%typescript.preferences.importModuleSpecifierEnding.minimal%","%typescript.preferences.importModuleSpecifierEnding.index%","%typescript.preferences.importModuleSpecifierEnding.js%"]},"javascript.preferences.jsxAttributeCompletionStyle":{"type":"string","scope":"language-overridable","enum":["auto","braces","none"],"description":"%typescript.preferences.jsxAttributeCompletionStyle%","markdownEnumDescriptions":["%javascript.preferences.jsxAttributeCompletionStyle.auto%","%typescript.preferences.jsxAttributeCompletionStyle.braces%","%typescript.preferences.jsxAttributeCompletionStyle.none%"],"default":"auto"},"typescript.preferences.jsxAttributeCompletionStyle":{"type":"string","scope":"language-overridable","enum":["auto","braces","none"],"description":"%typescript.preferences.jsxAttributeCompletionStyle%","markdownEnumDescriptions":["%typescript.preferences.jsxAttributeCompletionStyle.auto%","%typescript.preferences.jsxAttributeCompletionStyle.braces%","%typescript.preferences.jsxAttributeCompletionStyle.none%"],"default":"auto"},"typescript.preferences.includePackageJsonAutoImports":{"type":"string","markdownDescription":"%typescript.preferences.includePackageJsonAutoImports%","enumDescriptions":["%typescript.preferences.includePackageJsonAutoImports.auto%","%typescript.preferences.includePackageJsonAutoImports.on%","%typescript.preferences.includePackageJsonAutoImports.off%"],"enum":["auto","on","off"],"scope":"window","default":"auto"},"typescript.preferences.autoImportFileExcludePatterns":{"type":"array","items":{"type":"string"},"markdownDescription":"%typescript.preferences.autoImportFileExcludePatterns%","scope":"resource"},"javascript.preferences.autoImportFileExcludePatterns":{"type":"array","items":{"type":"string"},"markdownDescription":"%typescript.preferences.autoImportFileExcludePatterns%","scope":"resource"},"javascript.preferences.renameShorthandProperties":{"deprecationMessage":"%typescript.preferences.renameShorthandProperties.deprecationMessage%","scope":"language-overridable","type":"boolean","description":"%typescript.preferences.useAliasesForRenames%","default":true},"typescript.preferences.renameShorthandProperties":{"deprecationMessage":"%typescript.preferences.renameShorthandProperties.deprecationMessage%","scope":"language-overridable","type":"boolean","description":"%typescript.preferences.useAliasesForRenames%","default":true},"javascript.preferences.useAliasesForRenames":{"type":"boolean","default":true,"description":"%typescript.preferences.useAliasesForRenames%","scope":"language-overridable"},"typescript.preferences.useAliasesForRenames":{"type":"boolean","default":true,"description":"%typescript.preferences.useAliasesForRenames%","scope":"language-overridable"},"javascript.preferences.renameMatchingJsxTags":{"type":"boolean","default":true,"description":"%typescript.preferences.renameMatchingJsxTags%","scope":"language-overridable"},"typescript.preferences.renameMatchingJsxTags":{"type":"boolean","default":true,"description":"%typescript.preferences.renameMatchingJsxTags%","scope":"language-overridable"},"typescript.updateImportsOnFileMove.enabled":{"type":"string","scope":"resource","enum":["prompt","always","never"],"description":"%typescript.updateImportsOnFileMove.enabled%","markdownEnumDescriptions":["%typescript.updateImportsOnFileMove.enabled.prompt%","%typescript.updateImportsOnFileMove.enabled.always%","%typescript.updateImportsOnFileMove.enabled.never%"],"default":"prompt"},"javascript.updateImportsOnFileMove.enabled":{"type":"string","scope":"resource","enum":["prompt","always","never"],"description":"%typescript.updateImportsOnFileMove.enabled%","markdownEnumDescriptions":["%typescript.updateImportsOnFileMove.enabled.prompt%","%typescript.updateImportsOnFileMove.enabled.always%","%typescript.updateImportsOnFileMove.enabled.never%"],"default":"prompt"},"typescript.autoClosingTags":{"type":"boolean","default":true,"description":"%typescript.autoClosingTags%","scope":"language-overridable"},"javascript.autoClosingTags":{"type":"boolean","default":true,"description":"%typescript.autoClosingTags%","scope":"language-overridable"},"javascript.suggest.enabled":{"type":"boolean","default":true,"description":"%typescript.suggest.enabled%","scope":"language-overridable"},"typescript.suggest.enabled":{"type":"boolean","default":true,"description":"%typescript.suggest.enabled%","scope":"language-overridable"},"typescript.surveys.enabled":{"type":"boolean","default":true,"description":"%configuration.surveys.enabled%","scope":"window"},"typescript.tsserver.useSeparateSyntaxServer":{"default":true,"scope":"window","markdownDeprecationMessage":"%configuration.tsserver.useSeparateSyntaxServer.deprecation%","type":"boolean","description":"%configuration.tsserver.useSeparateSyntaxServer%"},"typescript.tsserver.useSyntaxServer":{"default":"auto","scope":"window","enum":["always","never","auto"],"enumDescriptions":["%configuration.tsserver.useSyntaxServer.always%","%configuration.tsserver.useSyntaxServer.never%","%configuration.tsserver.useSyntaxServer.auto%"],"description":"%configuration.tsserver.useSyntaxServer%","type":"string"},"typescript.experimental.aiQuickFix":{"type":"boolean","default":false,"description":"%typescript.experimental.aiQuickFix%","scope":"resource"},"typescript.tsserver.maxTsServerMemory":{"type":"number","default":3072,"description":"%configuration.tsserver.maxTsServerMemory%","scope":"window"},"typescript.tsserver.experimental.enableProjectDiagnostics":{"type":"boolean","scope":"window","description":"%configuration.tsserver.experimental.enableProjectDiagnostics%","tags":["experimental"],"default":false},"typescript.enablePromptUseWorkspaceTsdk":{"type":"boolean","default":false,"description":"%typescript.enablePromptUseWorkspaceTsdk%","scope":"window"},"typescript.tsserver.watchOptions":{"properties":{"synchronousWatchDirectory":{"description":"%configuration.tsserver.watchOptions.synchronousWatchDirectory%","type":"boolean"},"watchDirectory":{"description":"%configuration.tsserver.watchOptions.watchDirectory%","enumDescriptions":["%configuration.tsserver.watchOptions.watchDirectory.fixedChunkSizePolling%","%configuration.tsserver.watchOptions.watchDirectory.fixedPollingInterval%","%configuration.tsserver.watchOptions.watchDirectory.dynamicPriorityPolling%","%configuration.tsserver.watchOptions.watchDirectory.useFsEvents%"],"enum":["fixedChunkSizePolling","fixedPollingInterval","dynamicPriorityPolling","useFsEvents"],"default":"useFsEvents","type":"string"},"fallbackPolling":{"enum":["fixedPollingInterval","priorityPollingInterval","dynamicPriorityPolling"],"description":"%configuration.tsserver.watchOptions.fallbackPolling%","type":"string","enumDescriptions":["configuration.tsserver.watchOptions.fallbackPolling.fixedPollingInterval","configuration.tsserver.watchOptions.fallbackPolling.priorityPollingInterval","configuration.tsserver.watchOptions.fallbackPolling.dynamicPriorityPolling"]},"watchFile":{"description":"%configuration.tsserver.watchOptions.watchFile%","enumDescriptions":["%configuration.tsserver.watchOptions.watchFile.fixedChunkSizePolling%","%configuration.tsserver.watchOptions.watchFile.fixedPollingInterval%","%configuration.tsserver.watchOptions.watchFile.priorityPollingInterval%","%configuration.tsserver.watchOptions.watchFile.dynamicPriorityPolling%","%configuration.tsserver.watchOptions.watchFile.useFsEvents%","%configuration.tsserver.watchOptions.watchFile.useFsEventsOnParentDirectory%"],"enum":["fixedChunkSizePolling","fixedPollingInterval","priorityPollingInterval","dynamicPriorityPolling","useFsEvents","useFsEventsOnParentDirectory"],"default":"useFsEvents","type":"string"}},"description":"%configuration.tsserver.watchOptions%","type":"object","scope":"window"},"typescript.check.npmIsInstalled":{"type":"boolean","default":true,"markdownDescription":"%typescript.check.npmIsInstalled%","scope":"window"},"javascript.referencesCodeLens.enabled":{"type":"boolean","default":false,"description":"%javascript.referencesCodeLens.enabled%","scope":"window"},"javascript.referencesCodeLens.showOnAllFunctions":{"type":"boolean","default":false,"description":"%javascript.referencesCodeLens.showOnAllFunctions%","scope":"window"},"typescript.referencesCodeLens.enabled":{"type":"boolean","default":false,"description":"%typescript.referencesCodeLens.enabled%","scope":"window"},"typescript.referencesCodeLens.showOnAllFunctions":{"type":"boolean","default":false,"description":"%typescript.referencesCodeLens.showOnAllFunctions%","scope":"window"},"typescript.implementationsCodeLens.enabled":{"type":"boolean","default":false,"description":"%typescript.implementationsCodeLens.enabled%","scope":"window"},"typescript.tsserver.enableTracing":{"type":"boolean","default":false,"description":"%typescript.tsserver.enableTracing%","scope":"window"},"typescript.tsserver.log":{"type":"string","scope":"window","enum":["off","terse","normal","verbose"],"default":"off","description":"%typescript.tsserver.log%"},"javascript.suggest.completeFunctionCalls":{"type":"boolean","default":false,"description":"%configuration.suggest.completeFunctionCalls%","scope":"resource"},"typescript.suggest.completeFunctionCalls":{"type":"boolean","default":false,"description":"%configuration.suggest.completeFunctionCalls%","scope":"resource"},"javascript.suggest.includeAutomaticOptionalChainCompletions":{"type":"boolean","default":true,"description":"%configuration.suggest.includeAutomaticOptionalChainCompletions%","scope":"resource"},"typescript.suggest.includeAutomaticOptionalChainCompletions":{"type":"boolean","default":true,"description":"%configuration.suggest.includeAutomaticOptionalChainCompletions%","scope":"resource"},"typescript.inlayHints.parameterNames.enabled":{"type":"string","markdownDescription":"%configuration.inlayHints.parameterNames.enabled%","enumDescriptions":["%inlayHints.parameterNames.none%","%inlayHints.parameterNames.literals%","%inlayHints.parameterNames.all%"],"enum":["none","literals","all"],"scope":"resource","default":"none"},"typescript.workspaceSymbols.scope":{"type":"string","markdownDescription":"%typescript.workspaceSymbols.scope%","enumDescriptions":["%typescript.workspaceSymbols.scope.allOpenProjects%","%typescript.workspaceSymbols.scope.currentProject%"],"enum":["allOpenProjects","currentProject"],"scope":"window","default":"allOpenProjects"},"typescript.inlayHints.parameterNames.suppressWhenArgumentMatchesName":{"type":"boolean","default":true,"markdownDescription":"%configuration.inlayHints.parameterNames.suppressWhenArgumentMatchesName%","scope":"resource"},"javascript.suggest.classMemberSnippets.enabled":{"type":"boolean","default":true,"description":"%configuration.suggest.classMemberSnippets.enabled%","scope":"resource"},"typescript.inlayHints.parameterTypes.enabled":{"type":"boolean","default":false,"markdownDescription":"%configuration.inlayHints.parameterTypes.enabled%","scope":"resource"},"typescript.suggest.classMemberSnippets.enabled":{"type":"boolean","default":true,"description":"%configuration.suggest.classMemberSnippets.enabled%","scope":"resource"},"typescript.inlayHints.variableTypes.enabled":{"type":"boolean","default":false,"markdownDescription":"%configuration.inlayHints.variableTypes.enabled%","scope":"resource"},"typescript.inlayHints.variableTypes.suppressWhenTypeMatchesName":{"type":"boolean","default":true,"markdownDescription":"%configuration.inlayHints.variableTypes.suppressWhenTypeMatchesName%","scope":"resource"},"typescript.inlayHints.propertyDeclarationTypes.enabled":{"type":"boolean","default":false,"markdownDescription":"%configuration.inlayHints.propertyDeclarationTypes.enabled%","scope":"resource"},"typescript.inlayHints.functionLikeReturnTypes.enabled":{"type":"boolean","default":false,"markdownDescription":"%configuration.inlayHints.functionLikeReturnTypes.enabled%","scope":"resource"},"typescript.inlayHints.enumMemberValues.enabled":{"type":"boolean","default":false,"markdownDescription":"%configuration.inlayHints.enumMemberValues.enabled%","scope":"resource"},"javascript.inlayHints.parameterNames.enabled":{"type":"string","markdownDescription":"%configuration.inlayHints.parameterNames.enabled%","enumDescriptions":["%inlayHints.parameterNames.none%","%inlayHints.parameterNames.literals%","%inlayHints.parameterNames.all%"],"enum":["none","literals","all"],"scope":"resource","default":"none"},"javascript.inlayHints.parameterNames.suppressWhenArgumentMatchesName":{"type":"boolean","default":true,"markdownDescription":"%configuration.inlayHints.parameterNames.suppressWhenArgumentMatchesName%","scope":"resource"},"javascript.inlayHints.parameterTypes.enabled":{"type":"boolean","default":false,"markdownDescription":"%configuration.inlayHints.parameterTypes.enabled%","scope":"resource"},"javascript.inlayHints.variableTypes.enabled":{"type":"boolean","default":false,"markdownDescription":"%configuration.inlayHints.variableTypes.enabled%","scope":"resource"},"javascript.inlayHints.variableTypes.suppressWhenTypeMatchesName":{"type":"boolean","default":true,"markdownDescription":"%configuration.inlayHints.variableTypes.suppressWhenTypeMatchesName%","scope":"resource"},"javascript.inlayHints.propertyDeclarationTypes.enabled":{"type":"boolean","default":false,"markdownDescription":"%configuration.inlayHints.propertyDeclarationTypes.enabled%","scope":"resource"},"javascript.inlayHints.functionLikeReturnTypes.enabled":{"type":"boolean","default":false,"markdownDescription":"%configuration.inlayHints.functionLikeReturnTypes.enabled%","scope":"resource"},"javascript.inlayHints.enumMemberValues.enabled":{"type":"boolean","default":false,"markdownDescription":"%configuration.inlayHints.enumMemberValues.enabled%","scope":"resource"},"javascript.suggest.includeCompletionsForImportStatements":{"type":"boolean","default":true,"description":"%configuration.suggest.includeCompletionsForImportStatements%","scope":"resource"},"typescript.suggest.includeCompletionsForImportStatements":{"type":"boolean","default":true,"description":"%configuration.suggest.includeCompletionsForImportStatements%","scope":"resource"},"typescript.reportStyleChecksAsWarnings":{"type":"boolean","default":true,"description":"%typescript.reportStyleChecksAsWarnings%","scope":"window"},"typescript.validate.enable":{"type":"boolean","default":true,"description":"%typescript.validate.enable%","scope":"window"},"typescript.format.enable":{"type":"boolean","default":true,"description":"%typescript.format.enable%","scope":"window"},"typescript.format.insertSpaceAfterCommaDelimiter":{"type":"boolean","default":true,"description":"%format.insertSpaceAfterCommaDelimiter%","scope":"resource"},"javascript.suggest.autoImports":{"type":"boolean","default":true,"description":"%configuration.suggest.autoImports%","scope":"resource"},"typescript.format.insertSpaceAfterConstructor":{"type":"boolean","default":false,"description":"%format.insertSpaceAfterConstructor%","scope":"resource"},"typescript.suggest.autoImports":{"type":"boolean","default":true,"description":"%configuration.suggest.autoImports%","scope":"resource"},"typescript.format.insertSpaceAfterSemicolonInForStatements":{"type":"boolean","default":true,"description":"%format.insertSpaceAfterSemicolonInForStatements%","scope":"resource"},"typescript.format.insertSpaceBeforeAndAfterBinaryOperators":{"type":"boolean","default":true,"description":"%format.insertSpaceBeforeAndAfterBinaryOperators%","scope":"resource"},"typescript.suggest.completeJSDocs":{"type":"boolean","default":true,"description":"%configuration.suggest.completeJSDocs%","scope":"language-overridable"},"javascript.suggest.jsdoc.generateReturns":{"type":"boolean","default":true,"markdownDescription":"%configuration.suggest.jsdoc.generateReturns%","scope":"language-overridable"},"typescript.suggest.jsdoc.generateReturns":{"type":"boolean","default":true,"markdownDescription":"%configuration.suggest.jsdoc.generateReturns%","scope":"language-overridable"},"typescript.locale":{"default":"auto","markdownDescription":"%typescript.locale%","scope":"window","enum":["auto","de","es","en","fr","it","ja","ko","ru","zh-CN","zh-TW"],"type":"string"},"typescript.format.insertSpaceBeforeFunctionParenthesis":{"type":"boolean","default":false,"description":"%format.insertSpaceBeforeFunctionParenthesis%","scope":"resource"},"typescript.format.insertSpaceAfterOpeningAndBeforeClosingNonemptyParenthesis":{"type":"boolean","default":false,"description":"%format.insertSpaceAfterOpeningAndBeforeClosingNonemptyParenthesis%","scope":"resource"},"typescript.format.insertSpaceAfterOpeningAndBeforeClosingNonemptyBrackets":{"type":"boolean","default":false,"description":"%format.insertSpaceAfterOpeningAndBeforeClosingNonemptyBrackets%","scope":"resource"},"typescript.format.insertSpaceAfterOpeningAndBeforeClosingNonemptyBraces":{"type":"boolean","default":true,"description":"%format.insertSpaceAfterOpeningAndBeforeClosingNonemptyBraces%","scope":"resource"},"typescript.format.insertSpaceAfterOpeningAndBeforeClosingEmptyBraces":{"type":"boolean","default":true,"description":"%format.insertSpaceAfterOpeningAndBeforeClosingEmptyBraces%","scope":"resource"},"typescript.suggestionActions.enabled":{"type":"boolean","default":true,"description":"%typescript.suggestionActions.enabled%","scope":"resource"},"typescript.format.insertSpaceAfterOpeningAndBeforeClosingJsxExpressionBraces":{"type":"boolean","default":false,"description":"%format.insertSpaceAfterOpeningAndBeforeClosingJsxExpressionBraces%","scope":"resource"},"typescript.format.insertSpaceAfterTypeAssertion":{"type":"boolean","default":false,"description":"%format.insertSpaceAfterTypeAssertion%","scope":"resource"},"typescript.format.placeOpenBraceOnNewLineForFunctions":{"type":"boolean","default":false,"description":"%format.placeOpenBraceOnNewLineForFunctions%","scope":"resource"},"typescript.preferences.quoteStyle":{"type":"string","markdownDescription":"%typescript.preferences.quoteStyle%","scope":"language-overridable","enum":["auto","single","double"],"markdownEnumDescriptions":["%typescript.preferences.quoteStyle.auto%","%typescript.preferences.quoteStyle.single%","%typescript.preferences.quoteStyle.double%"],"default":"auto"},"typescript.format.placeOpenBraceOnNewLineForControlBlocks":{"type":"boolean","default":false,"description":"%format.placeOpenBraceOnNewLineForControlBlocks%","scope":"resource"},"typescript.tsdk":{"type":"string","markdownDescription":"%typescript.tsdk.desc%","scope":"window"},"typescript.tsserver.pluginPaths":{"description":"%typescript.tsserver.pluginPaths%","scope":"machine","type":"array","default":[],"items":{"description":"%typescript.tsserver.pluginPaths.item%","type":"string"}},"typescript.npm":{"type":"string","markdownDescription":"%typescript.npm%","scope":"machine"},"typescript.format.indentSwitchCase":{"type":"boolean","default":true,"description":"%format.indentSwitchCase%","scope":"resource"},"javascript.validate.enable":{"type":"boolean","default":true,"description":"%javascript.validate.enable%","scope":"window"},"javascript.format.enable":{"type":"boolean","default":true,"description":"%javascript.format.enable%","scope":"window"},"javascript.format.insertSpaceAfterCommaDelimiter":{"type":"boolean","default":true,"description":"%format.insertSpaceAfterCommaDelimiter%","scope":"resource"},"javascript.format.insertSpaceAfterConstructor":{"type":"boolean","default":false,"description":"%format.insertSpaceAfterConstructor%","scope":"resource"},"javascript.format.insertSpaceAfterSemicolonInForStatements":{"type":"boolean","default":true,"description":"%format.insertSpaceAfterSemicolonInForStatements%","scope":"resource"},"javascript.format.insertSpaceBeforeAndAfterBinaryOperators":{"type":"boolean","default":true,"description":"%format.insertSpaceBeforeAndAfterBinaryOperators%","scope":"resource"},"javascript.format.insertSpaceAfterKeywordsInControlFlowStatements":{"type":"boolean","default":true,"description":"%format.insertSpaceAfterKeywordsInControlFlowStatements%","scope":"resource"},"javascript.format.insertSpaceAfterFunctionKeywordForAnonymousFunctions":{"type":"boolean","default":true,"description":"%format.insertSpaceAfterFunctionKeywordForAnonymousFunctions%","scope":"resource"},"javascript.format.insertSpaceBeforeFunctionParenthesis":{"type":"boolean","default":false,"description":"%format.insertSpaceBeforeFunctionParenthesis%","scope":"resource"},"javascript.format.insertSpaceAfterOpeningAndBeforeClosingNonemptyParenthesis":{"type":"boolean","default":false,"description":"%format.insertSpaceAfterOpeningAndBeforeClosingNonemptyParenthesis%","scope":"resource"},"javascript.format.insertSpaceAfterOpeningAndBeforeClosingNonemptyBrackets":{"type":"boolean","default":false,"description":"%format.insertSpaceAfterOpeningAndBeforeClosingNonemptyBrackets%","scope":"resource"},"javascript.format.insertSpaceAfterOpeningAndBeforeClosingNonemptyBraces":{"type":"boolean","default":true,"description":"%format.insertSpaceAfterOpeningAndBeforeClosingNonemptyBraces%","scope":"resource"},"javascript.format.insertSpaceAfterOpeningAndBeforeClosingEmptyBraces":{"type":"boolean","default":true,"description":"%format.insertSpaceAfterOpeningAndBeforeClosingEmptyBraces%","scope":"resource"},"javascript.format.insertSpaceAfterOpeningAndBeforeClosingTemplateStringBraces":{"type":"boolean","default":false,"description":"%format.insertSpaceAfterOpeningAndBeforeClosingTemplateStringBraces%","scope":"resource"},"javascript.format.insertSpaceAfterOpeningAndBeforeClosingJsxExpressionBraces":{"type":"boolean","default":false,"description":"%format.insertSpaceAfterOpeningAndBeforeClosingJsxExpressionBraces%","scope":"resource"},"javascript.format.placeOpenBraceOnNewLineForFunctions":{"type":"boolean","default":false,"description":"%format.placeOpenBraceOnNewLineForFunctions%","scope":"resource"},"javascript.format.placeOpenBraceOnNewLineForControlBlocks":{"type":"boolean","default":false,"description":"%format.placeOpenBraceOnNewLineForControlBlocks%","scope":"resource"},"javascript.format.semicolons":{"type":"string","scope":"resource","enum":["ignore","insert","remove"],"enumDescriptions":["%format.semicolons.ignore%","%format.semicolons.insert%","%format.semicolons.remove%"],"description":"%format.semicolons%","default":"ignore"},"js\/ts.implicitProjectConfig.module":{"type":"string","markdownDescription":"%configuration.implicitProjectConfig.module%","scope":"window","enum":["CommonJS","AMD","System","UMD","ES6","ES2015","ES2020","ESNext","None","ES2022","Node12","NodeNext"],"default":"ESNext"},"javascript.preferGoToSourceDefinition":{"type":"boolean","default":false,"description":"%configuration.preferGoToSourceDefinition%","scope":"window"},"typescript.preferGoToSourceDefinition":{"type":"boolean","default":false,"description":"%configuration.preferGoToSourceDefinition%","scope":"window"},"typescript.tsserver.web.projectWideIntellisense.suppressSemanticErrors":{"type":"boolean","default":true,"description":"%configuration.tsserver.web.projectWideIntellisense.suppressSemanticErrors%","scope":"window"},"typescript.tsserver.web.projectWideIntellisense.enabled":{"type":"boolean","default":true,"description":"%configuration.tsserver.web.projectWideIntellisense.enabled%","scope":"window"},"typescript.suggest.objectLiteralMethodSnippets.enabled":{"type":"boolean","default":true,"description":"%configuration.suggest.objectLiteralMethodSnippets.enabled%","scope":"resource"},"typescript.format.semicolons":{"type":"string","scope":"resource","enum":["ignore","insert","remove"],"enumDescriptions":["%format.semicolons.ignore%","%format.semicolons.insert%","%format.semicolons.remove%"],"description":"%format.semicolons%","default":"ignore"},"javascript.suggestionActions.enabled":{"type":"boolean","default":true,"description":"%javascript.suggestionActions.enabled%","scope":"resource"},"typescript.suggest.paths":{"type":"boolean","default":true,"description":"%configuration.suggest.paths%","scope":"resource"},"javascript.suggest.completeJSDocs":{"type":"boolean","default":true,"description":"%configuration.suggest.completeJSDocs%","scope":"language-overridable"},"js\/ts.implicitProjectConfig.target":{"default":"ES2020","markdownDescription":"%configuration.implicitProjectConfig.target%","scope":"window","enum":["ES3","ES5","ES6","ES2015","ES2016","ES2017","ES2018","ES2019","ES2020","ES2021","ES2022","ESNext"],"type":"string"},"typescript.disableAutomaticTypeAcquisition":{"type":"boolean","markdownDescription":"%typescript.disableAutomaticTypeAcquisition%","scope":"window","tags":["usesOnlineServices"],"default":false},"javascript.preferences.quoteStyle":{"type":"string","markdownDescription":"%typescript.preferences.quoteStyle%","scope":"language-overridable","enum":["auto","single","double"],"markdownEnumDescriptions":["%typescript.preferences.quoteStyle.auto%","%typescript.preferences.quoteStyle.single%","%typescript.preferences.quoteStyle.double%"],"default":"auto"},"typescript.format.insertSpaceAfterOpeningAndBeforeClosingTemplateStringBraces":{"type":"boolean","default":false,"description":"%format.insertSpaceAfterOpeningAndBeforeClosingTemplateStringBraces%","scope":"resource"},"typescript.format.insertSpaceAfterFunctionKeywordForAnonymousFunctions":{"type":"boolean","default":true,"description":"%format.insertSpaceAfterFunctionKeywordForAnonymousFunctions%","scope":"resource"},"typescript.format.insertSpaceAfterKeywordsInControlFlowStatements":{"type":"boolean","default":true,"description":"%format.insertSpaceAfterKeywordsInControlFlowStatements%","scope":"resource"}}}